[
  {
    "slug": "2026-03-05-sen-johnson-blocks-iran-war-vote",
    "title": "Sen. Johnson blocks Iran war vote",
    "category": "politics",
    "source": "NPR Politics",
    "date": "March 05, 2026",
    "image_url": "https://i.ibb.co/kstYpBrd/91be0d61c528.png"
  },
  {
    "slug": "2026-03-05-china-robot-army-videos-exposed-as-ai-fakes",
    "title": "China robot army videos exposed as AI fakes",
    "category": "world",
    "source": "France 24",
    "date": "March 05, 2026",
    "image_url": "https://i.ibb.co/hJZVdByH/8cd3afa5b0bd.png"
  },
  {
    "slug": "2026-03-05-brazil-launches-hiking-trails-for-conservation",
    "title": "Brazil launches hiking trails for conservation",
    "category": "world",
    "source": "The Guardian World",
    "date": "March 05, 2026",
    "image_url": "https://i.ibb.co/23ZfsRYd/476f48f0d86e.png"
  },
  {
    "slug": "2026-03-05-gonzales-faces-ethics-probe-party-pressure",
    "title": "Gonzales faces ethics probe, party pressure",
    "category": "politics",
    "source": "NPR Politics",
    "date": "March 05, 2026",
    "image_url": "https://i.ibb.co/gbc98RHR/eb747f85abb8.png"
  },
  {
    "slug": "2026-03-05-minnesota-sues-over-medicaid-funding-cuts",
    "title": "Minnesota sues over Medicaid funding cuts",
    "category": "politics",
    "source": "NPR Politics",
    "date": "March 05, 2026",
    "image_url": "https://i.ibb.co/hR7PqS0k/a3438891e0c0.png"
  },
  {
    "slug": "2026-03-05-young-democrats-outraise-incumbent-rivals",
    "title": "Young Democrats outraise incumbent rivals",
    "category": "politics",
    "source": "NPR Politics",
    "date": "March 05, 2026",
    "image_url": "https://i.ibb.co/NdjBQcTj/b4045d68c038.png"
  },
  {
    "slug": "2026-03-05-trump-launches-iran-war-amid-norm-breaks",
    "title": "Trump launches Iran war amid norm breaks",
    "category": "politics",
    "source": "NPR Politics",
    "date": "March 05, 2026",
    "image_url": "https://i.ibb.co/ZRrkvzWQ/49fe841df33a.png"
  },
  {
    "slug": "2026-03-05-china-lowers-2026-growth-target-to-45-5",
    "title": "China lowers 2026 growth target to 4.5-5%",
    "category": "world",
    "source": "NPR News",
    "date": "March 05, 2026",
    "image_url": "https://i.ibb.co/b5WbSn3M/5d738ec4933b.png"
  },
  {
    "slug": "2026-03-05-australia-deploys-military-for-stranded-middle-east-citizens",
    "title": "Australia deploys military for stranded Middle East citizens",
    "category": "world",
    "source": "The Guardian World",
    "date": "March 05, 2026",
    "image_url": "https://i.ibb.co/67mMbkC9/9c036b8789fe.png"
  },
  {
    "slug": "2026-03-05-us-evacuates-americans-from-middle-east",
    "title": "U.S. evacuates Americans from Middle East",
    "category": "politics",
    "source": "NPR Politics",
    "date": "March 05, 2026",
    "image_url": "https://i.ibb.co/chRLT7JW/9cdf631444d5.png"
  },
  {
    "slug": "2026-03-05-off-market-sales-strategy-shows-uneven-results",
    "title": "Off-market sales strategy shows uneven results",
    "category": "business",
    "source": "Financial Times",
    "date": "March 05, 2026",
    "image_url": "https://i.ibb.co/Vk1Xwk2/4004fc77fcb7.png"
  },
  {
    "slug": "2026-03-04-australia-scraps-foi-bill-canada-backs-iran-action",
    "title": "Australia scraps FoI bill; Canada backs Iran action",
    "category": "world",
    "source": "The Guardian World",
    "date": "March 04, 2026",
    "image_url": "https://i.ibb.co/7tj1wjQG/6e6929145bbc.png"
  },
  {
    "slug": "2026-03-04-trump-nominee-cleared-for-public-lands-agency-role",
    "title": "Trump nominee cleared for public lands agency role",
    "category": "politics",
    "source": "NPR Politics",
    "date": "March 04, 2026",
    "image_url": "https://i.ibb.co/LhRBzqV2/1eb963cc8967.png"
  },
  {
    "slug": "2026-03-04-australians-return-from-middle-east-conflict",
    "title": "Australians return from Middle East conflict",
    "category": "world",
    "source": "The Guardian World",
    "date": "March 04, 2026",
    "image_url": "https://i.ibb.co/tpDGxYwB/9417bf90841c.png"
  },
  {
    "slug": "2026-03-04-australians-return-home-from-middle-east",
    "title": "Australians return home from Middle East",
    "category": "world",
    "source": "The Guardian World",
    "date": "March 04, 2026",
    "image_url": "https://i.ibb.co/3mZHWtDd/d806d42f01ff.png"
  },
  {
    "slug": "2026-03-04-meeks-addresses-iran-operations-war-powers",
    "title": "Meeks addresses Iran operations, war powers",
    "category": "politics",
    "source": "NPR Politics",
    "date": "March 04, 2026",
    "image_url": "https://i.ibb.co/WWdJnTnQ/4d380686c054.png"
  },
  {
    "slug": "2026-03-04-oscar-docs-tackle-cancer-prisons-iran-russia",
    "title": "Oscar docs tackle cancer, prisons, Iran, Russia",
    "category": "world",
    "source": "NPR News",
    "date": "March 04, 2026",
    "image_url": "https://i.ibb.co/8kPVmPd/9014b2ba07af.png"
  },
  {
    "slug": "2026-03-03-pm-addresses-stranded-australians-with-uae",
    "title": "PM addresses stranded Australians with UAE",
    "category": "world",
    "source": "The Guardian World",
    "date": "March 03, 2026",
    "image_url": "https://i.ibb.co/GfqzsZ7C/f4e242fd7e85.png"
  },
  {
    "slug": "2026-03-03-congress-votes-on-war-declaration-power",
    "title": "Congress votes on war declaration power",
    "category": "politics",
    "source": "NPR Politics",
    "date": "March 03, 2026"
  }
]